{
  "annotations": {
    "list": []
  },
  "editable": true,
  "fiscalYearStartMonth": 0,
  "graphTooltip": 1,
  "links": [
    {
      "asDropdown": false,
      "icon": "bolt",
      "includeVars": true,
      "keepTime": true,
      "tags": [],
      "targetBlank": false,
      "title": "HVAC",
      "tooltip": "View HVAC ventilation and energy details",
      "type": "link",
      "url": "/d/wago-hvac/hvac"
    },
    {
      "asDropdown": false,
      "icon": "dashboard",
      "includeVars": true,
      "keepTime": true,
      "tags": [],
      "targetBlank": false,
      "title": "Ruuvi Sensors",
      "tooltip": "View Ruuvi Bluetooth sensor data",
      "type": "link",
      "url": "/d/ruuvi-sensors/ruuvi-sensors"
    },
    {
      "asDropdown": false,
      "icon": "dashboard",
      "includeVars": true,
      "keepTime": true,
      "tags": [],
      "targetBlank": false,
      "title": "Light Status",
      "tooltip": "View light switch status by floor",
      "type": "link",
      "url": "/d/wago-lights/light-switch-status"
    }
  ],
  "liveNow": false,
  "panels": [
    {
      "datasource": {
        "type": "influxdb",
        "uid": "influxdb"
      },
      "fieldConfig": {
        "defaults": {
          "decimals": 1,
          "unit": "celsius"
        },
        "overrides": []
      },
      "gridPos": {
        "h": 16,
        "w": 12,
        "x": 0,
        "y": 0
      },
      "id": 15,
      "options": {
        "inlineEditing": false,
        "root": {
          "background": {
            "color": {
              "fixed": "transparent"
            },
            "image": {
              "fixed": "img/floorplan/2krs-vari.jpeg",
              "mode": "fixed"
            },
            "size": "contain"
          },
          "border": {
            "color": {
              "fixed": "transparent"
            }
          },
          "elements": [
            {
              "background": { "color": { "fixed": "rgba(0,0,0,0.4)" } },
              "border": { "color": { "fixed": "transparent" } },
              "config": { "align": "center", "color": { "fixed": "#cccccc" }, "size": 11, "text": { "fixed": "MH aikuiset", "mode": "fixed" }, "valign": "middle" },
              "name": "MH aikuiset label",
              "placement": { "height": 18, "left": 195, "top": 132, "width": 90 },
              "type": "metric-value"
            },
            {
              "background": { "color": { "fixed": "rgba(0,0,0,0.4)" } },
              "border": { "color": { "fixed": "transparent" } },
              "config": { "align": "center", "color": { "fixed": "#ffffff" }, "size": 16, "text": { "field": "MH_aikuiset", "fixed": "", "mode": "field" }, "valign": "middle" },
              "name": "MH aikuiset",
              "placement": { "height": 25, "left": 195, "top": 150, "width": 90 },
              "type": "metric-value"
            },
            {
              "background": { "color": { "fixed": "rgba(0,0,0,0.4)" } },
              "border": { "color": { "fixed": "transparent" } },
              "config": { "align": "center", "color": { "fixed": "#cccccc" }, "size": 11, "text": { "fixed": "Aula", "mode": "fixed" }, "valign": "middle" },
              "name": "Aula label",
              "placement": { "height": 18, "left": 370, "top": 362, "width": 90 },
              "type": "metric-value"
            },
            {
              "background": { "color": { "fixed": "rgba(0,0,0,0.4)" } },
              "border": { "color": { "fixed": "transparent" } },
              "config": { "align": "center", "color": { "fixed": "#ffffff" }, "size": 16, "text": { "field": "Ylakerran_aula", "fixed": "", "mode": "field" }, "valign": "middle" },
              "name": "Yläkerran aula",
              "placement": { "height": 25, "left": 370, "top": 380, "width": 90 },
              "type": "metric-value"
            },
            {
              "background": { "color": { "fixed": "rgba(0,0,0,0.4)" } },
              "border": { "color": { "fixed": "transparent" } },
              "config": { "align": "center", "color": { "fixed": "#cccccc" }, "size": 11, "text": { "fixed": "MH Aarni", "mode": "fixed" }, "valign": "middle" },
              "name": "MH Aarni label",
              "placement": { "height": 18, "left": 165, "top": 362, "width": 90 },
              "type": "metric-value"
            },
            {
              "background": { "color": { "fixed": "rgba(0,0,0,0.4)" } },
              "border": { "color": { "fixed": "transparent" } },
              "config": { "align": "center", "color": { "fixed": "#ffffff" }, "size": 16, "text": { "field": "MH_Aarni", "fixed": "", "mode": "field" }, "valign": "middle" },
              "name": "MH Aarni",
              "placement": { "height": 25, "left": 165, "top": 380, "width": 90 },
              "type": "metric-value"
            },
            {
              "background": { "color": { "fixed": "rgba(0,0,0,0.4)" } },
              "border": { "color": { "fixed": "transparent" } },
              "config": { "align": "center", "color": { "fixed": "#cccccc" }, "size": 11, "text": { "fixed": "MH Seela", "mode": "fixed" }, "valign": "middle" },
              "name": "MH Seela label",
              "placement": { "height": 18, "left": 600, "top": 362, "width": 90 },
              "type": "metric-value"
            },
            {
              "background": { "color": { "fixed": "rgba(0,0,0,0.4)" } },
              "border": { "color": { "fixed": "transparent" } },
              "config": { "align": "center", "color": { "fixed": "#ffffff" }, "size": 16, "text": { "field": "MH_Seela", "fixed": "", "mode": "field" }, "valign": "middle" },
              "name": "MH Seela",
              "placement": { "height": 25, "left": 600, "top": 380, "width": 90 },
              "type": "metric-value"
            }
          ],
          "name": "root",
          "type": "frame"
        }
      },
      "title": "2. kerros",
      "type": "canvas",
      "targets": [
        {
          "datasource": {
            "type": "influxdb",
            "uid": "influxdb"
          },
          "query": "from(bucket: \"building_automation\")\n  |> range(start: -24h)\n  |> filter(fn: (r) => r._measurement == \"rooms\")\n  |> filter(fn: (r) => r.room_type != \"pid\")\n  |> filter(fn: (r) => r.floor == \"2\")\n  |> last()\n  |> group()\n  |> pivot(rowKey: [\"_time\"], columnKey: [\"_field\"], valueColumn: \"_value\")",
          "refId": "A"
        }
      ]
    },
    {
      "datasource": {
        "type": "influxdb",
        "uid": "influxdb"
      },
      "fieldConfig": {
        "defaults": {
          "decimals": 1,
          "unit": "celsius"
        },
        "overrides": []
      },
      "gridPos": {
        "h": 16,
        "w": 12,
        "x": 12,
        "y": 0
      },
      "id": 16,
      "options": {
        "inlineEditing": false,
        "root": {
          "background": {
            "color": {
              "fixed": "transparent"
            },
            "image": {
              "fixed": "img/floorplan/1krs-vari.jpeg",
              "mode": "fixed"
            },
            "size": "contain"
          },
          "border": {
            "color": {
              "fixed": "transparent"
            }
          },
          "elements": [
            {
              "background": { "color": { "fixed": "rgba(0,0,0,0.4)" } },
              "border": { "color": { "fixed": "transparent" } },
              "config": { "align": "center", "color": { "fixed": "#cccccc" }, "size": 11, "text": { "fixed": "Sauna", "mode": "fixed" }, "valign": "middle" },
              "name": "Sauna label",
              "placement": { "height": 18, "left": 40, "top": 62, "width": 90 },
              "type": "metric-value"
            },
            {
              "background": { "color": { "fixed": "rgba(0,0,0,0.4)" } },
              "border": { "color": { "fixed": "transparent" } },
              "config": { "align": "center", "color": { "fixed": "#ffffff" }, "size": 16, "text": { "field": "Sauna", "fixed": "", "mode": "field" }, "valign": "middle" },
              "name": "Sauna",
              "placement": { "height": 25, "left": 40, "top": 80, "width": 90 },
              "type": "metric-value"
            },
            {
              "background": { "color": { "fixed": "rgba(0,0,0,0.4)" } },
              "border": { "color": { "fixed": "transparent" } },
              "config": { "align": "center", "color": { "fixed": "#cccccc" }, "size": 11, "text": { "fixed": "Keittiö", "mode": "fixed" }, "valign": "middle" },
              "name": "Keittiö label",
              "placement": { "height": 18, "left": 420, "top":  242, "width": 90 },
              "type": "metric-value"
            },
            {
              "background": { "color": { "fixed": "rgba(0,0,0,0.4)" } },
              "border": { "color": { "fixed": "transparent" } },
              "config": { "align": "center", "color": { "fixed": "#ffffff" }, "size": 16, "text": { "field": "Keittio", "fixed": "", "mode": "field" }, "valign": "middle" },
              "name": "Keittiö",
              "placement": { "height": 25, "left": 420, "top": 260, "width": 90 },
              "type": "metric-value"
            },
            {
              "background": { "color": { "fixed": "rgba(0,0,0,0.4)" } },
              "border": { "color": { "fixed": "transparent" } },
              "config": { "align": "center", "color": { "fixed": "#cccccc" }, "size": 11, "text": { "fixed": "Olohuone", "mode": "fixed" }, "valign": "middle" },
              "name": "Olohuone label",
              "placement": { "height": 18, "left": 600, "top": 102, "width": 90 },
              "type": "metric-value"
            },
            {
              "background": { "color": { "fixed": "rgba(0,0,0,0.4)" } },
              "border": { "color": { "fixed": "transparent" } },
              "config": { "align": "center", "color": { "fixed": "#ffffff" }, "size": 16, "text": { "field": "Olohuone", "fixed": "", "mode": "field" }, "valign": "middle" },
              "name": "Olohuone",
              "placement": { "height": 25, "left": 600, "top": 120, "width": 90 },
              "type": "metric-value"
            },
            {
              "background": { "color": { "fixed": "rgba(0,0,0,0.4)" } },
              "border": { "color": { "fixed": "transparent" } },
              "config": { "align": "center", "color": { "fixed": "#cccccc" }, "size": 11, "text": { "fixed": "Eteinen", "mode": "fixed" }, "valign": "middle" },
              "name": "Eteinen label",
              "placement": { "height": 18, "left": 240, "top": 182, "width": 90 },
              "type": "metric-value"
            },
            {
              "background": { "color": { "fixed": "rgba(0,0,0,0.4)" } },
              "border": { "color": { "fixed": "transparent" } },
              "config": { "align": "center", "color": { "fixed": "#ffffff" }, "size": 16, "text": { "field": "Eteinen", "fixed": "", "mode": "field" }, "valign": "middle" },
              "name": "Eteinen",
              "placement": { "height": 25, "left": 240, "top": 200, "width": 90 },
              "type": "metric-value"
            },
            {
              "background": { "color": { "fixed": "rgba(0,0,0,0.4)" } },
              "border": { "color": { "fixed": "transparent" } },
              "config": { "align": "center", "color": { "fixed": "#cccccc" }, "size": 11, "text": { "fixed": "Takka", "mode": "fixed" }, "valign": "middle" },
              "name": "Takka label",
              "placement": { "height": 18, "left": 470, "top": 102, "width": 90 },
              "type": "metric-value"
            },
            {
              "background": { "color": { "fixed": "rgba(0,0,0,0.4)" } },
              "border": { "color": { "fixed": "transparent" } },
              "config": { "align": "center", "color": { "fixed": "#ffffff" }, "size": 16, "text": { "field": "Takka", "fixed": "", "mode": "field" }, "valign": "middle" },
              "name": "Takka",
              "placement": { "height": 25, "left": 470, "top": 120, "width": 90 },
              "type": "metric-value"
            },
            {
              "background": { "color": { "fixed": "rgba(0,0,0,0.4)" } },
              "border": { "color": { "fixed": "transparent" } },
              "config": { "align": "center", "color": { "fixed": "#cccccc" }, "size": 11, "text": { "fixed": "MH alakerta", "mode": "fixed" }, "valign": "middle" },
              "name": "MH alakerta label",
              "placement": { "height": 18, "left": 60, "top": 242, "width": 90 },
              "type": "metric-value"
            },
            {
              "background": { "color": { "fixed": "rgba(0,0,0,0.4)" } },
              "border": { "color": { "fixed": "transparent" } },
              "config": { "align": "center", "color": { "fixed": "#ffffff" }, "size": 16, "text": { "field": "MH_alakerta", "fixed": "", "mode": "field" }, "valign": "middle" },
              "name": "MH alakerta",
              "placement": { "height": 25, "left": 60, "top": 260, "width": 90 },
              "type": "metric-value"
            },
            {
              "background": { "color": { "fixed": "rgba(0,0,0,0.6)" } },
              "border": { "color": { "fixed": "transparent" } },
              "config": { "align": "center", "color": { "fixed": "#cccccc" }, "size": 11, "text": { "fixed": "Ulkolämpötila", "mode": "fixed" }, "valign": "middle" },
              "name": "Ulkolämpötila label",
              "placement": { "height": 18, "left": 650, "top": 222, "width": 100 },
              "type": "metric-value"
            },
            {
              "background": { "color": { "fixed": "rgba(0,0,0,0.6)" } },
              "border": { "color": { "fixed": "transparent" } },
              "config": { "align": "center", "color": { "fixed": "#ffffff" }, "size": 16, "text": { "field": "Ulkolämpötila", "fixed": "", "mode": "field" }, "valign": "middle" },
              "name": "Ulkolämpötila",
              "placement": { "height": 25, "left": 650, "top": 240, "width": 100 },
              "type": "metric-value"
            }
          ],
          "name": "root",
          "type": "frame"
        }
      },
      "title": "1. kerros",
      "type": "canvas",
      "targets": [
        {
          "datasource": {
            "type": "influxdb",
            "uid": "influxdb"
          },
          "query": "from(bucket: \"building_automation\")\n  |> range(start: -24h)\n  |> filter(fn: (r) => r._measurement == \"rooms\")\n  |> filter(fn: (r) => r.room_type != \"pid\")\n  |> filter(fn: (r) => r.floor == \"1\")\n  |> last()\n  |> group()\n  |> pivot(rowKey: [\"_time\"], columnKey: [\"_field\"], valueColumn: \"_value\")",
          "refId": "A"
        },
        {
          "datasource": {
            "type": "influxdb",
            "uid": "influxdb"
          },
          "query": "from(bucket: \"building_automation\")\n  |> range(start: -1h)\n  |> filter(fn: (r) => r._measurement == \"ruuvi\")\n  |> filter(fn: (r) => r._field == \"temperature\")\n  |> filter(fn: (r) => r.sensor_name == \"Olohuone\" or r.sensor_name == \"Takka\" or r.sensor_name == \"Sauna\" or r.sensor_name == \"Ulkolämpötila\")\n  |> last()\n  |> map(fn: (r) => ({r with _field: r.sensor_name, _time: now()}))\n  |> group()\n  |> pivot(rowKey: [\"_time\"], columnKey: [\"_field\"], valueColumn: \"_value\")",
          "refId": "B"
        }
      ]
    },
    {
      "datasource": {
        "type": "influxdb",
        "uid": "influxdb"
      },
      "fieldConfig": {
        "defaults": {
          "color": {
            "mode": "palette-classic"
          },
          "custom": {
            "axisCenteredZero": false,
            "axisColorMode": "text",
            "axisLabel": "Lämpötila (°C)",
            "axisPlacement": "auto",
            "barAlignment": 0,
            "drawStyle": "line",
            "fillOpacity": 10,
            "gradientMode": "none",
            "hideFrom": {
              "legend": false,
              "tooltip": false,
              "viz": false
            },
            "lineInterpolation": "smooth",
            "lineWidth": 1,
            "pointSize": 5,
            "scaleDistribution": {
              "type": "linear"
            },
            "showPoints": "never",
            "spanNulls": 3600000,
            "stacking": {
              "group": "A",
              "mode": "none"
            },
            "thresholdsStyle": {
              "mode": "dashed"
            }
          },
          "mappings": [],
          "thresholds": {
            "mode": "absolute",
            "steps": [
              {
                "color": "transparent",
                "value": null
              },
              {
                "color": "rgba(150, 150, 150, 0.5)",
                "value": 22
              }
            ]
          },
          "unit": "celsius"
        },
        "overrides": [
          {
            "matcher": {
              "id": "byName",
              "options": "MH_Seela"
            },
            "properties": [
              {
                "id": "displayName",
                "value": "MH Seela"
              },
              {
                "id": "color",
                "value": {
                  "fixedColor": "green",
                  "mode": "fixed"
                }
              }
            ]
          },
          {
            "matcher": {
              "id": "byName",
              "options": "MH_Aarni"
            },
            "properties": [
              {
                "id": "displayName",
                "value": "MH Aarni"
              },
              {
                "id": "color",
                "value": {
                  "fixedColor": "yellow",
                  "mode": "fixed"
                }
              }
            ]
          },
          {
            "matcher": {
              "id": "byName",
              "options": "MH_aikuiset"
            },
            "properties": [
              {
                "id": "displayName",
                "value": "MH aikuiset"
              },
              {
                "id": "color",
                "value": {
                  "fixedColor": "orange",
                  "mode": "fixed"
                }
              }
            ]
          },
          {
            "matcher": {
              "id": "byName",
              "options": "MH_alakerta"
            },
            "properties": [
              {
                "id": "displayName",
                "value": "MH alakerta"
              },
              {
                "id": "color",
                "value": {
                  "fixedColor": "red",
                  "mode": "fixed"
                }
              }
            ]
          },
          {
            "matcher": {
              "id": "byName",
              "options": "Ulkolämpötila"
            },
            "properties": [
              {
                "id": "custom.axisPlacement",
                "value": "right"
              },
              {
                "id": "custom.axisLabel",
                "value": "Ulkolämpötila (°C)"
              },
              {
                "id": "color",
                "value": {
                  "fixedColor": "light-blue",
                  "mode": "fixed"
                }
              },
              {
                "id": "custom.lineStyle",
                "value": {
                  "fill": "dash",
                  "dash": [
                    10,
                    5
                  ]
                }
              },
              {
                "id": "custom.fillOpacity",
                "value": 0
              }
            ]
          }
        ]
      },
      "gridPos": {
        "h": 16,
        "w": 12,
        "x": 0,
        "y": 16
      },
      "id": 5,
      "options": {
        "legend": {
          "calcs": [
            "mean",
            "min",
            "max",
            "last"
          ],
          "displayMode": "table",
          "placement": "bottom",
          "showLegend": true
        },
        "tooltip": {
          "mode": "multi",
          "sort": "desc"
        }
      },
      "title": "Makuuhuoneiden lämpötilat",
      "type": "timeseries",
      "targets": [
        {
          "datasource": {
            "type": "influxdb",
            "uid": "influxdb"
          },
          "query": "from(bucket: \"building_automation\")\n  |> range(start: v.timeRangeStart, stop: v.timeRangeStop)\n  |> filter(fn: (r) => r._measurement == \"rooms\")\n  |> filter(fn: (r) => r.room_type == \"bedroom\")\n  |> aggregateWindow(every: v.windowPeriod, fn: mean, createEmpty: false)\n  |> keep(columns: [\"_time\", \"_value\", \"_field\"])",
          "refId": "A"
        },
        {
          "datasource": {
            "type": "influxdb",
            "uid": "influxdb"
          },
          "query": "from(bucket: \"building_automation\")\n  |> range(start: v.timeRangeStart, stop: v.timeRangeStop)\n  |> filter(fn: (r) => r._measurement == \"hvac\")\n  |> filter(fn: (r) => r._field == \"Ulkolampotila\")\n  |> aggregateWindow(every: v.windowPeriod, fn: mean, createEmpty: false)\n  |> map(fn: (r) => ({r with _field: \"Ulkolämpötila\"}))\n  |> keep(columns: [\"_time\", \"_value\", \"_field\"])",
          "refId": "B"
        }
      ]
    },
    {
      "datasource": {
        "type": "influxdb",
        "uid": "influxdb"
      },
      "fieldConfig": {
        "defaults": {
          "color": {
            "mode": "palette-classic"
          },
          "custom": {
            "axisCenteredZero": false,
            "axisColorMode": "text",
            "axisLabel": "Lämpötila (°C)",
            "axisPlacement": "auto",
            "barAlignment": 0,
            "drawStyle": "line",
            "fillOpacity": 10,
            "gradientMode": "none",
            "hideFrom": {
              "legend": false,
              "tooltip": false,
              "viz": false
            },
            "lineInterpolation": "smooth",
            "lineWidth": 1,
            "pointSize": 5,
            "scaleDistribution": {
              "type": "linear"
            },
            "showPoints": "never",
            "spanNulls": 3600000,
            "stacking": {
              "group": "A",
              "mode": "none"
            },
            "thresholdsStyle": {
              "mode": "dashed"
            }
          },
          "mappings": [],
          "thresholds": {
            "mode": "absolute",
            "steps": [
              {
                "color": "transparent",
                "value": null
              },
              {
                "color": "rgba(150, 150, 150, 0.5)",
                "value": 22
              }
            ]
          },
          "unit": "celsius"
        },
        "overrides": [
          {
            "matcher": {
              "id": "byName",
              "options": "Ylakerran_aula"
            },
            "properties": [
              {
                "id": "displayName",
                "value": "Yläkerran aula"
              },
              {
                "id": "color",
                "value": {
                  "fixedColor": "green",
                  "mode": "fixed"
                }
              }
            ]
          },
          {
            "matcher": {
              "id": "byName",
              "options": "Keittio"
            },
            "properties": [
              {
                "id": "displayName",
                "value": "Keittiö"
              },
              {
                "id": "color",
                "value": {
                  "fixedColor": "yellow",
                  "mode": "fixed"
                }
              }
            ]
          },
          {
            "matcher": {
              "id": "byName",
              "options": "Eteinen"
            },
            "properties": [
              {
                "id": "displayName",
                "value": "Eteinen"
              },
              {
                "id": "color",
                "value": {
                  "fixedColor": "orange",
                  "mode": "fixed"
                }
              }
            ]
          },
          {
            "matcher": {
              "id": "byName",
              "options": "Keittiö (Ruuvi)"
            },
            "properties": [
              {
                "id": "custom.lineStyle",
                "value": {
                  "fill": "dash",
                  "dash": [
                    10,
                    5
                  ]
                }
              },
              {
                "id": "color",
                "value": {
                  "fixedColor": "super-light-yellow",
                  "mode": "fixed"
                }
              }
            ]
          },
          {
            "matcher": {
              "id": "byName",
              "options": "Olohuone (Ruuvi)"
            },
            "properties": [
              {
                "id": "custom.lineStyle",
                "value": {
                  "fill": "dash",
                  "dash": [
                    10,
                    5
                  ]
                }
              },
              {
                "id": "color",
                "value": {
                  "fixedColor": "purple",
                  "mode": "fixed"
                }
              }
            ]
          },
          {
            "matcher": {
              "id": "byName",
              "options": "Ulkolämpötila"
            },
            "properties": [
              {
                "id": "custom.axisPlacement",
                "value": "right"
              },
              {
                "id": "custom.axisLabel",
                "value": "Ulkolämpötila (°C)"
              },
              {
                "id": "color",
                "value": {
                  "fixedColor": "light-blue",
                  "mode": "fixed"
                }
              },
              {
                "id": "custom.lineStyle",
                "value": {
                  "fill": "dash",
                  "dash": [
                    10,
                    5
                  ]
                }
              },
              {
                "id": "custom.fillOpacity",
                "value": 0
              }
            ]
          }
        ]
      },
      "gridPos": {
        "h": 16,
        "w": 12,
        "x": 12,
        "y": 16
      },
      "id": 6,
      "options": {
        "legend": {
          "calcs": [
            "mean",
            "min",
            "max",
            "last"
          ],
          "displayMode": "table",
          "placement": "bottom",
          "showLegend": true
        },
        "tooltip": {
          "mode": "multi",
          "sort": "desc"
        }
      },
      "title": "Yleiset tilat (aula, keittiö, eteinen)",
      "type": "timeseries",
      "targets": [
        {
          "datasource": {
            "type": "influxdb",
            "uid": "influxdb"
          },
          "query": "from(bucket: \"building_automation\")\n  |> range(start: v.timeRangeStart, stop: v.timeRangeStop)\n  |> filter(fn: (r) => r._measurement == \"rooms\")\n  |> filter(fn: (r) => r.room_type == \"common\")\n  |> aggregateWindow(every: v.windowPeriod, fn: mean, createEmpty: false)\n  |> keep(columns: [\"_time\", \"_value\", \"_field\"])",
          "refId": "A"
        },
        {
          "datasource": {
            "type": "influxdb",
            "uid": "influxdb"
          },
          "query": "from(bucket: \"building_automation\")\n  |> range(start: v.timeRangeStart, stop: v.timeRangeStop)\n  |> filter(fn: (r) => r._measurement == \"ruuvi\")\n  |> filter(fn: (r) => r._field == \"temperature\")\n  |> filter(fn: (r) => r.sensor_name == \"Keittiö\" or r.sensor_name == \"Olohuone\")\n  |> aggregateWindow(every: v.windowPeriod, fn: mean, createEmpty: false)\n  |> map(fn: (r) => ({r with _field: r.sensor_name + \" (Ruuvi)\"}))\n  |> keep(columns: [\"_time\", \"_value\", \"_field\"])",
          "refId": "B"
        },
        {
          "datasource": {
            "type": "influxdb",
            "uid": "influxdb"
          },
          "query": "from(bucket: \"building_automation\")\n  |> range(start: v.timeRangeStart, stop: v.timeRangeStop)\n  |> filter(fn: (r) => r._measurement == \"hvac\")\n  |> filter(fn: (r) => r._field == \"Ulkolampotila\")\n  |> aggregateWindow(every: v.windowPeriod, fn: mean, createEmpty: false)\n  |> map(fn: (r) => ({r with _field: \"Ulkolämpötila\"}))\n  |> keep(columns: [\"_time\", \"_value\", \"_field\"])",
          "refId": "C"
        }
      ]
    },
    {
      "datasource": {
        "type": "influxdb",
        "uid": "influxdb"
      },
      "fieldConfig": {
        "defaults": {
          "color": {
            "mode": "palette-classic"
          },
          "custom": {
            "axisCenteredZero": false,
            "axisColorMode": "text",
            "axisLabel": "Lämpötila (°C)",
            "axisPlacement": "auto",
            "barAlignment": 0,
            "drawStyle": "line",
            "fillOpacity": 10,
            "gradientMode": "none",
            "hideFrom": {
              "legend": false,
              "tooltip": false,
              "viz": false
            },
            "lineInterpolation": "smooth",
            "lineWidth": 1,
            "pointSize": 5,
            "scaleDistribution": {
              "type": "linear"
            },
            "showPoints": "never",
            "spanNulls": 3600000,
            "stacking": {
              "group": "A",
              "mode": "none"
            },
            "thresholdsStyle": {
              "mode": "off"
            }
          },
          "mappings": [],
          "thresholds": {
            "mode": "absolute",
            "steps": [
              {
                "color": "green",
                "value": null
              }
            ]
          },
          "unit": "celsius"
        },
        "overrides": [
          {
            "matcher": {
              "id": "byName",
              "options": "Kellari"
            },
            "properties": [
              {
                "id": "displayName",
                "value": "Kellari"
              }
            ]
          },
          {
            "matcher": {
              "id": "byName",
              "options": "Kellari_eteinen"
            },
            "properties": [
              {
                "id": "displayName",
                "value": "Kellarin eteinen"
              }
            ]
          }
        ]
      },
      "gridPos": {
        "h": 12,
        "w": 12,
        "x": 0,
        "y": 32
      },
      "id": 7,
      "options": {
        "legend": {
          "calcs": [
            "mean",
            "min",
            "max",
            "last"
          ],
          "displayMode": "table",
          "placement": "bottom",
          "showLegend": true
        },
        "tooltip": {
          "mode": "multi",
          "sort": "desc"
        }
      },
      "title": "Kellarin lämpötilat",
      "type": "timeseries",
      "targets": [
        {
          "datasource": {
            "type": "influxdb",
            "uid": "influxdb"
          },
          "query": "from(bucket: \"building_automation\")\n  |> range(start: v.timeRangeStart, stop: v.timeRangeStop)\n  |> filter(fn: (r) => r._measurement == \"rooms\")\n  |> filter(fn: (r) => r.room_type == \"basement\")\n  |> aggregateWindow(every: v.windowPeriod, fn: mean, createEmpty: false)\n  |> keep(columns: [\"_time\", \"_value\", \"_field\"])",
          "refId": "A"
        }
      ]
    },
    {
      "datasource": {
        "type": "influxdb",
        "uid": "influxdb"
      },
      "fieldConfig": {
        "defaults": {
          "color": {
            "mode": "palette-classic"
          },
          "custom": {
            "axisCenteredZero": false,
            "axisColorMode": "text",
            "axisLabel": "Lämpötila (°C)",
            "axisPlacement": "auto",
            "barAlignment": 0,
            "drawStyle": "line",
            "fillOpacity": 10,
            "gradientMode": "none",
            "hideFrom": {
              "legend": false,
              "tooltip": false,
              "viz": false
            },
            "lineInterpolation": "smooth",
            "lineWidth": 1,
            "pointSize": 5,
            "scaleDistribution": {
              "type": "linear"
            },
            "showPoints": "never",
            "spanNulls": 3600000,
            "stacking": {
              "group": "A",
              "mode": "none"
            },
            "thresholdsStyle": {
              "mode": "off"
            }
          },
          "mappings": [],
          "thresholds": {
            "mode": "absolute",
            "steps": [
              {
                "color": "green",
                "value": null
              }
            ]
          },
          "unit": "celsius"
        },
        "overrides": [
          {
            "matcher": {
              "id": "byName",
              "options": "Sauna"
            },
            "properties": [
              {
                "id": "color",
                "value": {
                  "fixedColor": "red",
                  "mode": "fixed"
                }
              }
            ]
          },
          {
            "matcher": {
              "id": "byName",
              "options": "Kosteus"
            },
            "properties": [
              {
                "id": "custom.axisPlacement",
                "value": "right"
              },
              {
                "id": "unit",
                "value": "percent"
              },
              {
                "id": "custom.axisLabel",
                "value": "Kosteus (%)"
              },
              {
                "id": "color",
                "value": {
                  "fixedColor": "blue",
                  "mode": "fixed"
                }
              },
              {
                "id": "custom.fillOpacity",
                "value": 5
              },
              {
                "id": "custom.lineStyle",
                "value": {
                  "fill": "dash",
                  "dash": [
                    10,
                    5
                  ]
                }
              }
            ]
          }
        ]
      },
      "gridPos": {
        "h": 12,
        "w": 12,
        "x": 12,
        "y": 32
      },
      "id": 14,
      "options": {
        "legend": {
          "calcs": [
            "mean",
            "min",
            "max",
            "last"
          ],
          "displayMode": "table",
          "placement": "bottom",
          "showLegend": true
        },
        "tooltip": {
          "mode": "multi",
          "sort": "desc"
        }
      },
      "title": "Saunan lämpötila",
      "type": "timeseries",
      "targets": [
        {
          "datasource": {
            "type": "influxdb",
            "uid": "influxdb"
          },
          "query": "from(bucket: \"building_automation\")\n  |> range(start: v.timeRangeStart, stop: v.timeRangeStop)\n  |> filter(fn: (r) => r._measurement == \"ruuvi\")\n  |> filter(fn: (r) => r.sensor_name == \"Sauna\")\n  |> filter(fn: (r) => r._field == \"temperature\" or r._field == \"humidity\")\n  |> aggregateWindow(every: v.windowPeriod, fn: mean, createEmpty: false)\n  |> map(fn: (r) => ({r with _field: if r._field == \"temperature\" then \"Sauna\" else \"Kosteus\"}))\n  |> keep(columns: [\"_time\", \"_value\", \"_field\"])",
          "refId": "A"
        }
      ]
    },
    {
      "datasource": {
        "type": "influxdb",
        "uid": "influxdb"
      },
      "fieldConfig": {
        "defaults": {
          "color": {
            "mode": "palette-classic"
          },
          "custom": {
            "axisCenteredZero": false,
            "axisColorMode": "text",
            "axisLabel": "PID summa (%)",
            "axisPlacement": "auto",
            "barAlignment": 0,
            "drawStyle": "line",
            "fillOpacity": 20,
            "gradientMode": "opacity",
            "hideFrom": {
              "legend": false,
              "tooltip": false,
              "viz": false
            },
            "lineInterpolation": "smooth",
            "lineWidth": 2,
            "pointSize": 5,
            "scaleDistribution": {
              "type": "linear"
            },
            "showPoints": "never",
            "spanNulls": 3600000,
            "stacking": {
              "group": "A",
              "mode": "normal"
            },
            "thresholdsStyle": {
              "mode": "off"
            }
          },
          "mappings": [],
          "min": 0,
          "thresholds": {
            "mode": "absolute",
            "steps": [
              {
                "color": "green",
                "value": null
              }
            ]
          },
          "unit": "percent"
        },
        "overrides": [
          {
            "matcher": {
              "id": "byName",
              "options": "2. kerros"
            },
            "properties": [
              {
                "id": "color",
                "value": {
                  "fixedColor": "orange",
                  "mode": "fixed"
                }
              }
            ]
          },
          {
            "matcher": {
              "id": "byName",
              "options": "1. kerros"
            },
            "properties": [
              {
                "id": "color",
                "value": {
                  "fixedColor": "green",
                  "mode": "fixed"
                }
              }
            ]
          },
          {
            "matcher": {
              "id": "byName",
              "options": "Kellari"
            },
            "properties": [
              {
                "id": "color",
                "value": {
                  "fixedColor": "blue",
                  "mode": "fixed"
                }
              }
            ]
          }
        ]
      },
      "gridPos": {
        "h": 8,
        "w": 24,
        "x": 0,
        "y": 44
      },
      "id": 10,
      "options": {
        "legend": {
          "calcs": [
            "mean",
            "min",
            "max",
            "last"
          ],
          "displayMode": "table",
          "placement": "bottom",
          "showLegend": true
        },
        "tooltip": {
          "mode": "multi",
          "sort": "desc"
        }
      },
      "title": "Lämmitystarve kerroksittain (PID summa)",
      "type": "timeseries",
      "targets": [
        {
          "datasource": {
            "type": "influxdb",
            "uid": "influxdb"
          },
          "query": "from(bucket: \"building_automation\")\n  |> range(start: v.timeRangeStart, stop: v.timeRangeStop)\n  |> filter(fn: (r) => r._measurement == \"rooms\")\n  |> filter(fn: (r) => r.room_type == \"pid\")\n  |> aggregateWindow(every: v.windowPeriod, fn: mean, createEmpty: false)\n  |> group(columns: [\"_time\", \"floor\"])\n  |> sum()\n  |> map(fn: (r) => ({_time: r._time, _value: r._value, _field: if r.floor == \"2\" then \"2. kerros\" else if r.floor == \"1\" then \"1. kerros\" else \"Kellari\"}))\n  |> group(columns: [\"_field\"])",
          "refId": "A"
        }
      ]
    },
    {
      "datasource": {
        "type": "influxdb",
        "uid": "influxdb"
      },
      "fieldConfig": {
        "defaults": {
          "color": {
            "mode": "thresholds"
          },
          "custom": {
            "fillOpacity": 80,
            "lineWidth": 0,
            "spanNulls": false
          },
          "mappings": [
            {
              "options": {
                "from": 0,
                "result": {
                  "color": "blue",
                  "index": 0,
                  "text": "Pois"
                },
                "to": 1
              },
              "type": "range"
            },
            {
              "options": {
                "from": 1,
                "result": {
                  "color": "yellow",
                  "index": 1,
                  "text": "Osittain"
                },
                "to": 99
              },
              "type": "range"
            },
            {
              "options": {
                "from": 99,
                "result": {
                  "color": "red",
                  "index": 2,
                  "text": "Täysi"
                },
                "to": 101
              },
              "type": "range"
            }
          ],
          "thresholds": {
            "mode": "absolute",
            "steps": [
              {
                "color": "blue",
                "value": null
              },
              {
                "color": "yellow",
                "value": 1
              },
              {
                "color": "red",
                "value": 99
              }
            ]
          },
          "unit": "percent"
        },
        "overrides": [
          {
            "matcher": {
              "id": "byName",
              "options": "MH_Seela_PID"
            },
            "properties": [
              {
                "id": "displayName",
                "value": "MH Seela"
              }
            ]
          },
          {
            "matcher": {
              "id": "byName",
              "options": "MH_Aarni_PID"
            },
            "properties": [
              {
                "id": "displayName",
                "value": "MH Aarni"
              }
            ]
          },
          {
            "matcher": {
              "id": "byName",
              "options": "MH_aikuiset_PID"
            },
            "properties": [
              {
                "id": "displayName",
                "value": "MH aikuiset"
              }
            ]
          },
          {
            "matcher": {
              "id": "byName",
              "options": "MH_alakerta_PID"
            },
            "properties": [
              {
                "id": "displayName",
                "value": "MH alakerta"
              }
            ]
          },
          {
            "matcher": {
              "id": "byName",
              "options": "Ylakerran_aula_PID"
            },
            "properties": [
              {
                "id": "displayName",
                "value": "Yläkerran aula"
              }
            ]
          },
          {
            "matcher": {
              "id": "byName",
              "options": "Keittio_PID"
            },
            "properties": [
              {
                "id": "displayName",
                "value": "Keittiö"
              }
            ]
          },
          {
            "matcher": {
              "id": "byName",
              "options": "Eteinen_PID"
            },
            "properties": [
              {
                "id": "displayName",
                "value": "Eteinen"
              }
            ]
          },
          {
            "matcher": {
              "id": "byName",
              "options": "Kellari_PID"
            },
            "properties": [
              {
                "id": "displayName",
                "value": "Kellari"
              }
            ]
          },
          {
            "matcher": {
              "id": "byName",
              "options": "Kellari_eteinen_PID"
            },
            "properties": [
              {
                "id": "displayName",
                "value": "Kellarin eteinen"
              }
            ]
          }
        ]
      },
      "gridPos": {
        "h": 8,
        "w": 24,
        "x": 0,
        "y": 52
      },
      "id": 11,
      "options": {
        "alignValue": "center",
        "legend": {
          "displayMode": "list",
          "placement": "bottom",
          "showLegend": true
        },
        "mergeValues": true,
        "rowHeight": 0.8,
        "showValue": "auto",
        "tooltip": {
          "mode": "single",
          "sort": "none"
        }
      },
      "title": "Lämmityksen tila huoneittain",
      "type": "state-timeline",
      "targets": [
        {
          "datasource": {
            "type": "influxdb",
            "uid": "influxdb"
          },
          "query": "from(bucket: \"building_automation\")\n  |> range(start: v.timeRangeStart, stop: v.timeRangeStop)\n  |> filter(fn: (r) => r._measurement == \"rooms\")\n  |> filter(fn: (r) => r.room_type == \"pid\")\n  |> aggregateWindow(every: v.windowPeriod, fn: mean, createEmpty: false)\n  |> keep(columns: [\"_time\", \"_value\", \"_field\"])",
          "refId": "A"
        }
      ]
    }
  ],
  "refresh": "30s",
  "schemaVersion": 38,
  "style": "dark",
  "tags": [
    "building-automation",
    "wago"
  ],
  "templating": {
    "list": []
  },
  "time": {
    "from": "now-7d",
    "to": "now"
  },
  "timepicker": {
    "refresh_intervals": [
      "5s",
      "10s",
      "30s",
      "1m",
      "5m",
      "15m",
      "30m",
      "1h"
    ],
    "time_options": [
      "5m",
      "15m",
      "1h",
      "6h",
      "12h",
      "24h",
      "2d",
      "7d",
      "30d"
    ]
  },
  "timezone": "Europe/Helsinki",
  "title": "Temperature Overview",
  "uid": "wago-overview",
  "version": 3,
  "weekStart": ""
}